{
    "formatVersion": 1,
    "passTypeIdentifier": "pass.com.retapcard.loyalty",
    "teamIdentifier": "78S7N29429",
    "organizationName": "ReTap",
    "description": "ReTap Loyalty Card",
    "logoText": "ReTap",
    "foregroundColor": "rgb(255, 255, 255)",
    "backgroundColor": "rgb(255, 49, 49)",
    "labelColor": "rgb(255, 255, 255)",
    "storeCard": {
      "primaryFields": [],
      "secondaryFields": []
    },
    "barcode": {
      "format": "PKBarcodeFormatQR",
      "message": "retap_card",
      "messageEncoding": "iso-8859-1"
    }
  }